<annotation>
	<folder>n07718747</folder>
	<filename>n07718747_11918</filename>
	<source>
		<database>ILSVRC_2013</database>
	</source>
	<size>
		<width>500</width>
		<height>375</height>
	</size>
	<object>
		<name>n07718747</name>
		<bndbox>
			<xmin>98</xmin>
			<xmax>472</xmax>
			<ymin>44</ymin>
			<ymax>373</ymax>
		</bndbox>
	</object>
	<object>
		<name>n07718747</name>
		<bndbox>
			<xmin>66</xmin>
			<xmax>136</xmax>
			<ymin>243</ymin>
			<ymax>321</ymax>
		</bndbox>
	</object>
	<object>
		<name>n07718747</name>
		<bndbox>
			<xmin>405</xmin>
			<xmax>474</xmax>
			<ymin>289</ymin>
			<ymax>359</ymax>
		</bndbox>
	</object>
</annotation>
