<annotation>
	<folder>n01982650</folder>
	<filename>n01982650_12859</filename>
	<source>
		<database>ILSVRC_2013</database>
	</source>
	<size>
		<width>350</width>
		<height>263</height>
	</size>
	<object>
		<name>n01982650</name>
		<bndbox>
			<xmin>189</xmin>
			<xmax>349</xmax>
			<ymin>27</ymin>
			<ymax>198</ymax>
		</bndbox>
	</object>
	<object>
		<name>n01982650</name>
		<bndbox>
			<xmin>66</xmin>
			<xmax>215</xmax>
			<ymin>1</ymin>
			<ymax>165</ymax>
		</bndbox>
	</object>
	<object>
		<name>n01982650</name>
		<bndbox>
			<xmin>1</xmin>
			<xmax>66</xmax>
			<ymin>0</ymin>
			<ymax>129</ymax>
		</bndbox>
	</object>
</annotation>
