<annotation>
	<folder>n03814639</folder>
	<filename>n03814639_12070</filename>
	<source>
		<database>ILSVRC_2013</database>
	</source>
	<size>
		<width>500</width>
		<height>332</height>
	</size>
	<object>
		<name>n03814639</name>
		<bndbox>
			<xmin>334</xmin>
			<xmax>411</xmax>
			<ymin>128</ymin>
			<ymax>180</ymax>
		</bndbox>
	</object>
	<object>
		<name>n00007846</name>
		<bndbox>
			<xmin>281</xmin>
			<xmax>498</xmax>
			<ymin>88</ymin>
			<ymax>330</ymax>
		</bndbox>
	</object>
</annotation>
