<annotation>
	<folder>n02924116</folder>
	<filename>n02924116_101707</filename>
	<source>
		<database>ILSVRC_2013</database>
	</source>
	<size>
		<width>500</width>
		<height>327</height>
	</size>
	<object>
		<name>n02924116</name>
		<bndbox>
			<xmin>37</xmin>
			<xmax>452</xmax>
			<ymin>63</ymin>
			<ymax>259</ymax>
		</bndbox>
	</object>
	<object>
		<name>n02924116</name>
		<bndbox>
			<xmin>430</xmin>
			<xmax>473</xmax>
			<ymin>86</ymin>
			<ymax>217</ymax>
		</bndbox>
	</object>
	<object>
		<name>n02924116</name>
		<bndbox>
			<xmin>453</xmin>
			<xmax>499</xmax>
			<ymin>91</ymin>
			<ymax>220</ymax>
		</bndbox>
	</object>
</annotation>
