<annotation>
	<folder>n04332243</folder>
	<filename>n04332243_1068</filename>
	<source>
		<database>ILSVRC_2013</database>
	</source>
	<size>
		<width>333</width>
		<height>500</height>
	</size>
	<object>
		<name>n04332243</name>
		<bndbox>
			<xmin>43</xmin>
			<xmax>301</xmax>
			<ymin>0</ymin>
			<ymax>208</ymax>
		</bndbox>
	</object>
	<object>
		<name>n04332243</name>
		<bndbox>
			<xmin>0</xmin>
			<xmax>142</xmax>
			<ymin>96</ymin>
			<ymax>340</ymax>
		</bndbox>
	</object>
	<object>
		<name>n04332243</name>
		<bndbox>
			<xmin>135</xmin>
			<xmax>330</xmax>
			<ymin>202</ymin>
			<ymax>466</ymax>
		</bndbox>
	</object>
	<object>
		<name>n04332243</name>
		<bndbox>
			<xmin>25</xmin>
			<xmax>256</xmax>
			<ymin>335</ymin>
			<ymax>498</ymax>
		</bndbox>
	</object>
</annotation>
