<annotation>
	<folder>n02419796</folder>
	<filename>n02419796_11002</filename>
	<source>
		<database>ILSVRC_2013</database>
	</source>
	<size>
		<width>500</width>
		<height>267</height>
	</size>
	<object>
		<name>n02419796</name>
		<bndbox>
			<xmin>41</xmin>
			<xmax>116</xmax>
			<ymin>131</ymin>
			<ymax>168</ymax>
		</bndbox>
	</object>
	<object>
		<name>n02419796</name>
		<bndbox>
			<xmin>182</xmin>
			<xmax>211</xmax>
			<ymin>108</ymin>
			<ymax>151</ymax>
		</bndbox>
	</object>
	<object>
		<name>n02419796</name>
		<bndbox>
			<xmin>284</xmin>
			<xmax>308</xmax>
			<ymin>96</ymin>
			<ymax>145</ymax>
		</bndbox>
	</object>
</annotation>
