<annotation>
	<folder>n07745940</folder>
	<filename>n07745940_12824</filename>
	<source>
		<database>ILSVRC_2013</database>
	</source>
	<size>
		<width>250</width>
		<height>250</height>
	</size>
	<object>
		<name>n07745940</name>
		<bndbox>
			<xmin>84</xmin>
			<xmax>146</xmax>
			<ymin>82</ymin>
			<ymax>164</ymax>
		</bndbox>
	</object>
	<object>
		<name>n07745940</name>
		<bndbox>
			<xmin>147</xmin>
			<xmax>225</xmax>
			<ymin>104</ymin>
			<ymax>181</ymax>
		</bndbox>
	</object>
	<object>
		<name>n07745940</name>
		<bndbox>
			<xmin>159</xmin>
			<xmax>233</xmax>
			<ymin>42</ymin>
			<ymax>101</ymax>
		</bndbox>
	</object>
	<object>
		<name>n07745940</name>
		<bndbox>
			<xmin>81</xmin>
			<xmax>162</xmax>
			<ymin>3</ymin>
			<ymax>58</ymax>
		</bndbox>
	</object>
	<object>
		<name>n07745940</name>
		<bndbox>
			<xmin>49</xmin>
			<xmax>107</xmax>
			<ymin>134</ymin>
			<ymax>206</ymax>
		</bndbox>
	</object>
	<object>
		<name>n07745940</name>
		<bndbox>
			<xmin>27</xmin>
			<xmax>94</xmax>
			<ymin>43</ymin>
			<ymax>131</ymax>
		</bndbox>
	</object>
</annotation>
