<annotation>
	<folder>n04254680</folder>
	<filename>n04254680_13262</filename>
	<source>
		<database>ILSVRC_2013</database>
	</source>
	<size>
		<width>500</width>
		<height>375</height>
	</size>
	<object>
		<name>n04254680</name>
		<bndbox>
			<xmin>193</xmin>
			<xmax>214</xmax>
			<ymin>96</ymin>
			<ymax>117</ymax>
		</bndbox>
	</object>
	<object>
		<name>n00007846</name>
		<bndbox>
			<xmin>44</xmin>
			<xmax>85</xmax>
			<ymin>212</ymin>
			<ymax>344</ymax>
		</bndbox>
	</object>
	<object>
		<name>n00007846</name>
		<bndbox>
			<xmin>191</xmin>
			<xmax>278</xmax>
			<ymin>186</ymin>
			<ymax>324</ymax>
		</bndbox>
	</object>
	<object>
		<name>n00007846</name>
		<bndbox>
			<xmin>339</xmin>
			<xmax>397</xmax>
			<ymin>209</ymin>
			<ymax>357</ymax>
		</bndbox>
	</object>
	<object>
		<name>n00007846</name>
		<bndbox>
			<xmin>275</xmin>
			<xmax>360</xmax>
			<ymin>181</ymin>
			<ymax>344</ymax>
		</bndbox>
	</object>
	<object>
		<name>n00007846</name>
		<bndbox>
			<xmin>447</xmin>
			<xmax>499</xmax>
			<ymin>215</ymin>
			<ymax>349</ymax>
		</bndbox>
	</object>
	<object>
		<name>n00007846</name>
		<bndbox>
			<xmin>0</xmin>
			<xmax>21</xmax>
			<ymin>182</ymin>
			<ymax>280</ymax>
		</bndbox>
	</object>
</annotation>
