<annotation>
	<folder>n07720875</folder>
	<filename>n07720875_1078</filename>
	<source>
		<database>ILSVRC_2013</database>
	</source>
	<size>
		<width>333</width>
		<height>500</height>
	</size>
	<object>
		<name>n07720875</name>
		<bndbox>
			<xmin>47</xmin>
			<xmax>331</xmax>
			<ymin>75</ymin>
			<ymax>397</ymax>
		</bndbox>
	</object>
	<object>
		<name>n07720875</name>
		<bndbox>
			<xmin>0</xmin>
			<xmax>152</xmax>
			<ymin>0</ymin>
			<ymax>255</ymax>
		</bndbox>
	</object>
	<object>
		<name>n07720875</name>
		<bndbox>
			<xmin>184</xmin>
			<xmax>331</xmax>
			<ymin>13</ymin>
			<ymax>166</ymax>
		</bndbox>
	</object>
</annotation>
