<annotation>
	<folder>n03124170</folder>
	<filename>n03124170_10949</filename>
	<source>
		<database>ILSVRC_2013</database>
	</source>
	<size>
		<width>375</width>
		<height>500</height>
	</size>
	<object>
		<name>n00007846</name>
		<bndbox>
			<xmin>102</xmin>
			<xmax>260</xmax>
			<ymin>72</ymin>
			<ymax>498</ymax>
		</bndbox>
	</object>
	<object>
		<name>n03124170</name>
		<bndbox>
			<xmin>141</xmin>
			<xmax>240</xmax>
			<ymin>121</ymin>
			<ymax>162</ymax>
		</bndbox>
	</object>
</annotation>
